Metadata-Version: 1.1
Name: hangman-sm
Version: 0.0.1
Summary: a basic game of hangman
Home-page: UNKNOWN
Author: SM
Author-email: namefir19@gmail.com
License: MIT
Keywords: hangman,game
Platform: UNKNOWN
Classifier: Development Status :: 5 - Production/Stable
Classifier: Intended Audience :: Other Audience
Classifier: Operating System :: Microsoft :: Windows :: Windows 10
Classifier: License :: OSI Approved :: MIT License
Classifier: Programming Language :: Python :: 3
